casmarine/__init__.py
casmarine/cserial.py
casmarine/csocket.py
casmarine-1.6.2.dist-info/licenses/LICENSE
casmarine-1.6.2.dist-info/METADATA
casmarine-1.6.2.dist-info/WHEEL
casmarine-1.6.2.dist-info/top_level.txt
casmarine-1.6.2.dist-info/RECORD
