Metadata-Version: 2.4
Name: casmarine
Version: 1.6.2
Summary: Extendable communication library with support for various protocols for the use of CASMarine ROV team
Home-page: https://github.com/CASMarine/Communication
Author: Furkan Kırlangıç, Begüm İpek, Oğuzhan Furkan Ocak, Ahmet Enes Şimşek
Author-email: enes.simsek@std.yildiz.edu.tr
Project-URL: Bug Tracker, https://github.com/CASMarine/Communication/issues
Classifier: Programming Language :: Python :: 3
Classifier: License :: OSI Approved :: MIT License
Classifier: Operating System :: OS Independent
Requires-Python: >=3.8
License-File: LICENSE
Requires-Dist: pyserial
Requires-Dist: crccheck
Requires-Dist: stm32loader
Requires-Dist: requests
Requires-Dist: packaging
Dynamic: author
Dynamic: author-email
Dynamic: classifier
Dynamic: description-content-type
Dynamic: home-page
Dynamic: license-file
Dynamic: project-url
Dynamic: requires-dist
Dynamic: requires-python
Dynamic: summary
